<annotation>
	<folder>train-data</folder>
	<filename>Pin on -_BTS 방탄소년단_-.jpg</filename>
	<path>/Users/irenechang/Desktop/PORTFOLIO/Summer 2021/detect-bts-faces/train-data/Pin on -_BTS 방탄소년단_-.jpg</path>
	<source>
		<database>Unknown</database>
	</source>
	<size>
		<width>337</width>
		<height>600</height>
		<depth>3</depth>
	</size>
	<segmented>0</segmented>
	<object>
		<name>v</name>
		<pose>Unspecified</pose>
		<truncated>0</truncated>
		<difficult>0</difficult>
		<bndbox>
			<xmin>92</xmin>
			<ymin>115</ymin>
			<xmax>153</xmax>
			<ymax>188</ymax>
		</bndbox>
	</object>
	<object>
		<name>jimin</name>
		<pose>Unspecified</pose>
		<truncated>0</truncated>
		<difficult>0</difficult>
		<bndbox>
			<xmin>245</xmin>
			<ymin>126</ymin>
			<xmax>309</xmax>
			<ymax>193</ymax>
		</bndbox>
	</object>
	<object>
		<name>jin</name>
		<pose>Unspecified</pose>
		<truncated>0</truncated>
		<difficult>0</difficult>
		<bndbox>
			<xmin>248</xmin>
			<ymin>248</ymin>
			<xmax>295</xmax>
			<ymax>304</ymax>
		</bndbox>
	</object>
	<object>
		<name>rm</name>
		<pose>Unspecified</pose>
		<truncated>0</truncated>
		<difficult>0</difficult>
		<bndbox>
			<xmin>144</xmin>
			<ymin>255</ymin>
			<xmax>197</xmax>
			<ymax>324</ymax>
		</bndbox>
	</object>
	<object>
		<name>suga</name>
		<pose>Unspecified</pose>
		<truncated>0</truncated>
		<difficult>0</difficult>
		<bndbox>
			<xmin>35</xmin>
			<ymin>258</ymin>
			<xmax>90</xmax>
			<ymax>327</ymax>
		</bndbox>
	</object>
	<object>
		<name>jhope</name>
		<pose>Unspecified</pose>
		<truncated>0</truncated>
		<difficult>0</difficult>
		<bndbox>
			<xmin>32</xmin>
			<ymin>384</ymin>
			<xmax>96</xmax>
			<ymax>456</ymax>
		</bndbox>
	</object>
	<object>
		<name>jungkook</name>
		<pose>Unspecified</pose>
		<truncated>0</truncated>
		<difficult>0</difficult>
		<bndbox>
			<xmin>184</xmin>
			<ymin>372</ymin>
			<xmax>253</xmax>
			<ymax>453</ymax>
		</bndbox>
	</object>
</annotation>
